forward_backward/__init__.py
forward_backward-0.1.0.dist-info/licenses/LICENSE
forward_backward-0.1.0.dist-info/METADATA
forward_backward-0.1.0.dist-info/WHEEL
forward_backward-0.1.0.dist-info/top_level.txt
forward_backward-0.1.0.dist-info/RECORD
